PyNuclei/PyNuclei.py
PyNuclei/__init__.py
PyNuclei/poc.py
PyNuclei/static/.config
PyNuclei/static/font.ttf
pynuclei-1.4.4.dist-info/licenses/LICENSE
pynuclei-1.4.4.dist-info/METADATA
pynuclei-1.4.4.dist-info/WHEEL
pynuclei-1.4.4.dist-info/top_level.txt
pynuclei-1.4.4.dist-info/RECORD
