Metadata-Version: 2.4
Name: PyNuclei
Version: 1.4.4
Summary: PyNuclei is an unofficial python library for Nuclei Scanner.
Home-page: https://github.com/kushvaibhav/PyNuclei/
Author: Vaibhav Kushwaha
Author-email: vaibhavkush.007@gmail.com
Classifier: Programming Language :: Python :: 3
Classifier: License :: OSI Approved :: MIT License
Classifier: Operating System :: OS Independent
Requires-Python: >=3.8
License-File: LICENSE
Requires-Dist: PyYAML
Requires-Dist: requests
Requires-Dist: fake_useragent
Requires-Dist: Pillow<=10.4.0
Dynamic: author
Dynamic: author-email
Dynamic: classifier
Dynamic: description
Dynamic: description-content-type
Dynamic: home-page
Dynamic: license-file
Dynamic: requires-dist
Dynamic: requires-python
Dynamic: summary
